Projects/UART/main.v
module top (
    input wire btn2,
    input wire clk,
    input wire btn1,
    input wire uartRx,
    output wire uartTx,
    output wire [5:0] led 
);

reg [7:0] data;
reg [5:0] ascii_counter;
reg [23:0] micros;
reg [7:0] rx_data; // Keep this as reg to be assigned in always block

always @(posedge btn1) begin

    if (btn2) begin
        ascii_counter <= 0;
        data <= 0;
    end else begin
            data <= 65 + ascii_counter;
            ascii_counter <= ascii_counter + 1;

            if (ascii_counter == 25) begin
                ascii_counter <= 0;
            end
    end

end

// always @(posedge clk ) begin
//     micros <= micros + 1;
//     if(micros == 2330)begin
//         micros <= 0;
//         data <= 65 + ascii_counter;
//         ascii_counter <= ascii_counter + 1;

//         if (ascii_counter == 25) begin
//             ascii_counter <= 0;
//         end
//     end
// end

localparam clock = 27000000;
localparam baud = 115200;

wire [5:0] not_led;

assign led = ~(not_led);

UART uart (
    .rst(btn2), 
    .clk(clk), 
    .tx_buffer(data), 
    .baud_div(clock/baud - 1), 
    .TX(uartTx),
    .RX(uartRx),
    .tx_busy(),
    .rx_buffer(not_led) // Keep as reg in UART module for assignment
);

endmodule


module UART (
    input wire rst,
    input wire clk,
    input wire [7:0] tx_buffer,
    input wire [15:0] baud_div,
    input wire RX,
    output reg [7:0] rx_buffer,
    output reg rx_int,
    output reg TX,          
    output reg tx_busy
);

reg [16:0] baud_counter_tx;
reg [7:0] last_tx_buffer;

reg [1:0] tx_state;
localparam IDLE = 0, START = 1, DATA = 2, STOP = 3;

reg [3:0] bit_indexer_tx;

always @(posedge clk or posedge rst) begin
    if (rst == 1) begin
        tx_state <= IDLE;
        last_tx_buffer <= 0;
        baud_counter_tx <= 0;
        bit_indexer_tx <= 0;
        tx_busy <= 0;
        TX <= 1; // Idle state for TX line
    end else begin
        case (tx_state)
            IDLE: begin
                
                if ((tx_buffer != last_tx_buffer) && (tx_busy == 0)) begin
                    tx_state <= START;
                    last_tx_buffer <= tx_buffer;
                    tx_busy <= 1; // transmission begins

                    TX <= 0; // Start bit
                    bit_indexer_tx <= 0;
                    
                end
            end

            START: begin
                if (baud_counter_tx == baud_div) begin
                    baud_counter_tx <= 0;
                    tx_state <= DATA;

                    TX <= last_tx_buffer[bit_indexer_tx];
                    bit_indexer_tx <= 1;
                    

                end else begin
                    baud_counter_tx <= baud_counter_tx + 1;
                end
            end

            DATA: begin
                if (baud_counter_tx == baud_div) begin
                    baud_counter_tx <= 0;

                    if (bit_indexer_tx < 8) begin
                        TX <= last_tx_buffer[bit_indexer_tx];
                        bit_indexer_tx <= bit_indexer_tx + 1;
                    end else begin
                        TX <= 1; // Stop bit
                        tx_state <= STOP;
                    end

                end else begin
                    baud_counter_tx <= baud_counter_tx + 1;
                end
            end

            STOP: begin
                if (baud_counter_tx == baud_div) begin
                    baud_counter_tx <= 0;
                    tx_state <= IDLE;

                    tx_busy <= 0; // Transmission done
                end else begin
                    baud_counter_tx <= baud_counter_tx + 1;
                end
            end
        endcase
    end
end


reg [16:0] baud_counter_rx;

reg [1:0] rx_state;
reg [7:0] rx_shift_data;
reg [3:0] bit_indexer_rx;


always @(posedge clk  or posedge rst) begin

if (rst == 1) begin
    rx_state <= IDLE;
    baud_counter_rx <= 0;
    bit_indexer_rx <= 0;
    rx_shift_data <= 0;
    rx_int <= 0;
    rx_buffer <= 0;
end else begin

    case (rx_state)
        IDLE : begin
            if(RX == 0) begin
                rx_state <= START;
                baud_counter_rx <= 0;
            end
        end

        START : begin
            baud_counter_rx <= baud_counter_rx + 1;

                if(baud_counter_rx == (baud_div >> 1)) begin // go half way (/2) and sample at the middle of the start bit
                    baud_counter_rx <= 0;
                    if (RX == 0) begin                  // if still the bit is low, valid start bit
                        rx_state <= DATA;
                        bit_indexer_rx <= 4'h0;
                    end
                    else
                        rx_state <= IDLE;               // invalid RX state goes back to IDLE
                end
        end
        DATA : begin
            baud_counter_rx <= baud_counter_rx + 1;
            
            if(baud_counter_rx == baud_div) begin   // this time look for the full length of baud div, which will result into the mid of first bit
                rx_shift_data[bit_indexer_rx] <= RX;
                bit_indexer_rx <= bit_indexer_rx + 1;
                baud_counter_rx <= 0;

                if (bit_indexer_rx == 8) begin
                    rx_state <= STOP;
                    rx_buffer <= rx_shift_data;
                end
            end
        end

        STOP : begin
            if(RX == 0) begin           // invalid rx data
                rx_state <= IDLE;
                rx_shift_data <= 0;
                rx_buffer <= 0;
            end else begin
                rx_int <= 1;    // assert the int signal
                baud_counter_rx <= baud_counter_rx + 1;
                
                if(baud_counter_rx == (baud_div >> 1)) begin
                    rx_int <= 0; // dessert the INT signal
                    rx_state <= IDLE;
                end
            end
        end

    endcase
end
    
end

endmodule

Projects/UART/tb/uart_rx_tb.v
`timescale 1ns / 1ps

module UART_RX_tb();

// Testbench signals
reg clk;
reg rst;
reg RX;
reg [15:0] baud_div;
wire [7:0] rx_buffer;
wire rx_int;

// Instantiate UART module
UART uart_inst (
    .rst(rst),
    .clk(clk),
    .RX(RX),
    .rx_buffer(rx_buffer),
    .baud_div(baud_div),
    .rx_int(rx_int)
);

// Clock generation (27 MHz clock)
always #18.35 clk = ~clk;  // 27 MHz clock, period = 37 ns

// UART frame generator task
task send_uart_frame;
    input [7:0] data;  // Data to send
    integer i;

    begin
        // Start bit (low)
        RX <= 0;
        #(baud_div * 37);  // Wait for one baud period (divided by clock frequency)

        // Data bits (LSB first)
        for (i = 0; i < 8; i = i + 1) begin
            RX <= data[i];
            #(baud_div * 37);  // Wait for one baud period for each bit
        end

        // Stop bit (high)
        RX <= 1;
        #(baud_div * 37);  // Wait for one baud period
    end
endtask

initial begin
    // Initialize signals
    clk = 0;
    rst = 0;
    RX = 1;  // Idle line
    baud_div = 233;  // Baud divider for 115200 baud at 27 MHz clock

    // Apply reset
    rst = 1;
    #100;  // Hold reset for 100ns
    rst = 0;

    // Test 1: Send 0x55 (binary 01010101) over UART
    #1000;  // Wait for a few clock cycles after reset
    send_uart_frame(8'h55);  // Send 0x55
    #1000;  // Wait for some time

    // Check if rx_buffer has received 0x55 and rx_int was asserted
    if (rx_buffer == 8'h55) begin
        $display("Test 1 Passed: Received 0x55 correctly");
    end else begin
        $display("Test 1 Failed: Expected 0x55, but received %h", rx_buffer);
    end

    // Test 2: Send 0xAA (binary 10101010) over UART
    send_uart_frame(8'hAA);  // Send 0xAA
    #1000;  // Wait for some time

    // Check if rx_buffer has received 0xAA and rx_int was asserted
    if (rx_buffer == 8'hAA) begin
        $display("Test 2 Passed: Received 0xAA correctly");
    end else begin
        $display("Test 2 Failed: Expected 0xAA, but received %h", rx_buffer);
    end

    // Test completed
    $finish;
end

// Dump signals for waveform viewing (optional)
initial begin
    $dumpfile("uart_rx_waveform.vcd");  // Create dump file for GTKWave
    $dumpvars(0, UART_RX_tb);           // Dump all signals
end

endmodule

Projects/UART/tb/uart_rx_waveform.vcd
$date
	Sat Sep 28 16:01:13 2024
$end
$version
	Icarus Verilog
$end
$timescale
	1ps
$end
$scope module UART_RX_tb $end
$var wire 1 ! rx_int $end
$var wire 8 " rx_buffer [7:0] $end
$var reg 1 # RX $end
$var reg 16 $ baud_div [15:0] $end
$var reg 1 % clk $end
$var reg 1 & rst $end
$scope module uart_inst $end
$var wire 1 # RX $end
$var wire 16 ' baud_div [15:0] $end
$var wire 1 % clk $end
$var wire 1 & rst $end
$var wire 8 ( tx_buffer [7:0] $end
$var parameter 32 ) DATA $end
$var parameter 32 * IDLE $end
$var parameter 32 + START $end
$var parameter 32 , STOP $end
$var reg 1 - TX $end
$var reg 17 . baud_counter_rx [16:0] $end
$var reg 17 / baud_counter_tx [16:0] $end
$var reg 4 0 bit_indexer_rx [3:0] $end
$var reg 4 1 bit_indexer_tx [3:0] $end
$var reg 8 2 last_tx_buffer [7:0] $end
$var reg 8 3 rx_buffer [7:0] $end
$var reg 1 ! rx_int $end
$var reg 8 4 rx_shift_data [7:0] $end
$var reg 2 5 rx_state [1:0] $end
$var reg 1 6 tx_busy $end
$var reg 2 7 tx_state [1:0] $end
$upscope $end
$scope task send_uart_frame $end
$var reg 8 8 data [7:0] $end
$var integer 32 9 i [31:0] $end
$upscope $end
$upscope $end
$enddefinitions $end
$comment Show the parameter values. $end
$dumpall
b11 ,
b1 +
b0 *
b10 )
$end
#0
$dumpvars
bx 9
bx 8
b0 7
06
b0 5
b0 4
b0 3
b0 2
b0 1
b0 0
b0 /
b0 .
1-
bz (
b11101001 '
1&
0%
b11101001 $
1#
b0 "
0!
$end
#18350
1%
#36700
0%
#55050
1%
#73400
0%
#91750
1%
#100000
0&
#110100
0%
#128450
1%
#146800
0%
#165150
1%
#183500
0%
#201850
1%
#220200
0%
#238550
1%
#256900
0%
#275250
1%
#293600
0%
#311950
1%
#330300
0%
#348650
1%
#367000
0%
#385350
1%
#403700
0%
#422050
1%
#440400
0%
#458750
1%
#477100
0%
#495450
1%
#513800
0%
#532150
1%
#550500
0%
#568850
1%
#587200
0%
#605550
1%
#623900
0%
#642250
1%
#660600
0%
#678950
1%
#697300
0%
#715650
1%
#734000
0%
#752350
1%
#770700
0%
#789050
1%
#807400
0%
#825750
1%
#844100
0%
#862450
1%
#880800
0%
#899150
1%
#917500
0%
#935850
1%
#954200
0%
#972550
1%
#990900
0%
#1009250
1%
#1027600
0%
#1045950
1%
#1064300
0%
#1082650
1%
#1100000
0#
b1010101 8
#1101000
0%
#1119350
b1 5
1%
#1137700
0%
#1156050
b1 .
1%
#1174400
0%
#1192750
b10 .
1%
#1211100
0%
#1229450
b11 .
1%
#1247800
0%
#1266150
b100 .
1%
#1284500
0%
#1302850
b101 .
1%
#1321200
0%
#1339550
b110 .
1%
#1357900
0%
#1376250
b111 .
1%
#1394600
0%
#1412950
b1000 .
1%
#1431300
0%
#1449650
b1001 .
1%
#1468000
0%
#1486350
b1010 .
1%
#1504700
0%
#1523050
b1011 .
1%
#1541400
0%
#1559750
b1100 .
1%
#1578100
0%
#1596450
b1101 .
1%
#1614800
0%
#1633150
b1110 .
1%
#1651500
0%
#1669850
b1111 .
1%
#1688200
0%
#1706550
b10000 .
1%
#1724900
0%
#1743250
b10001 .
1%
#1761600
0%
#1779950
b10010 .
1%
#1798300
0%
#1816650
b10011 .
1%
#1835000
0%
#1853350
b10100 .
1%
#1871700
0%
#1890050
b10101 .
1%
#1908400
0%
#1926750
b10110 .
1%
#1945100
0%
#1963450
b10111 .
1%
#1981800
0%
#2000150
b11000 .
1%
#2018500
0%
#2036850
b11001 .
1%
#2055200
0%
#2073550
b11010 .
1%
#2091900
0%
#2110250
b11011 .
1%
#2128600
0%
#2146950
b11100 .
1%
#2165300
0%
#2183650
b11101 .
1%
#2202000
0%
#2220350
b11110 .
1%
#2238700
0%
#2257050
b11111 .
1%
#2275400
0%
#2293750
b100000 .
1%
#2312100
0%
#2330450
b100001 .
1%
#2348800
0%
#2367150
b100010 .
1%
#2385500
0%
#2403850
b100011 .
1%
#2422200
0%
#2440550
b100100 .
1%
#2458900
0%
#2477250
b100101 .
1%
#2495600
0%
#2513950
b100110 .
1%
#2532300
0%
#2550650
b100111 .
1%
#2569000
0%
#2587350
b101000 .
1%
#2605700
0%
#2624050
b101001 .
1%
#2642400
0%
#2660750
b101010 .
1%
#2679100
0%
#2697450
b101011 .
1%
#2715800
0%
#2734150
b101100 .
1%
#2752500
0%
#2770850
b101101 .
1%
#2789200
0%
#2807550
b101110 .
1%
#2825900
0%
#2844250
b101111 .
1%
#2862600
0%
#2880950
b110000 .
1%
#2899300
0%
#2917650
b110001 .
1%
#2936000
0%
#2954350
b110010 .
1%
#2972700
0%
#2991050
b110011 .
1%
#3009400
0%
#3027750
b110100 .
1%
#3046100
0%
#3064450
b110101 .
1%
#3082800
0%
#3101150
b110110 .
1%
#3119500
0%
#3137850
b110111 .
1%
#3156200
0%
#3174550
b111000 .
1%
#3192900
0%
#3211250
b111001 .
1%
#3229600
0%
#3247950
b111010 .
1%
#3266300
0%
#3284650
b111011 .
1%
#3303000
0%
#3321350
b111100 .
1%
#3339700
0%
#3358050
b111101 .
1%
#3376400
0%
#3394750
b111110 .
1%
#3413100
0%
#3431450
b111111 .
1%
#3449800
0%
#3468150
b1000000 .
1%
#3486500
0%
#3504850
b1000001 .
1%
#3523200
0%
#3541550
b1000010 .
1%
#3559900
0%
#3578250
b1000011 .
1%
#3596600
0%
#3614950
b1000100 .
1%
#3633300
0%
#3651650
b1000101 .
1%
#3670000
0%
#3688350
b1000110 .
1%
#3706700
0%
#3725050
b1000111 .
1%
#3743400
0%
#3761750
b1001000 .
1%
#3780100
0%
#3798450
b1001001 .
1%
#3816800
0%
#3835150
b1001010 .
1%
#3853500
0%
#3871850
b1001011 .
1%
#3890200
0%
#3908550
b1001100 .
1%
#3926900
0%
#3945250
b1001101 .
1%
#3963600
0%
#3981950
b1001110 .
1%
#4000300
0%
#4018650
b1001111 .
1%
#4037000
0%
#4055350
b1010000 .
1%
#4073700
0%
#4092050
b1010001 .
1%
#4110400
0%
#4128750
b1010010 .
1%
#4147100
0%
#4165450
b1010011 .
1%
#4183800
0%
#4202150
b1010100 .
1%
#4220500
0%
#4238850
b1010101 .
1%
#4257200
0%
#4275550
b1010110 .
1%
#4293900
0%
#4312250
b1010111 .
1%
#4330600
0%
#4348950
b1011000 .
1%
#4367300
0%
#4385650
b1011001 .
1%
#4404000
0%
#4422350
b1011010 .
1%
#4440700
0%
#4459050
b1011011 .
1%
#4477400
0%
#4495750
b1011100 .
1%
#4514100
0%
#4532450
b1011101 .
1%
#4550800
0%
#4569150
b1011110 .
1%
#4587500
0%
#4605850
b1011111 .
1%
#4624200
0%
#4642550
b1100000 .
1%
#4660900
0%
#4679250
b1100001 .
1%
#4697600
0%
#4715950
b1100010 .
1%
#4734300
0%
#4752650
b1100011 .
1%
#4771000
0%
#4789350
b1100100 .
1%
#4807700
0%
#4826050
b1100101 .
1%
#4844400
0%
#4862750
b1100110 .
1%
#4881100
0%
#4899450
b1100111 .
1%
#4917800
0%
#4936150
b1101000 .
1%
#4954500
0%
#4972850
b1101001 .
1%
#4991200
0%
#5009550
b1101010 .
1%
#5027900
0%
#5046250
b1101011 .
1%
#5064600
0%
#5082950
b1101100 .
1%
#5101300
0%
#5119650
b1101101 .
1%
#5138000
0%
#5156350
b1101110 .
1%
#5174700
0%
#5193050
b1101111 .
1%
#5211400
0%
#5229750
b1110000 .
1%
#5248100
0%
#5266450
b1110001 .
1%
#5284800
0%
#5303150
b1110010 .
1%
#5321500
0%
#5339850
b1110011 .
1%
#5358200
0%
#5376550
b1110100 .
1%
#5394900
0%
#5413250
b10 5
b0 .
1%
#5431600
0%
#5449950
b1 .
1%
#5468300
0%
#5486650
b10 .
1%
#5505000
0%
#5523350
b11 .
1%
#5541700
0%
#5560050
b100 .
1%
#5578400
0%
#5596750
b101 .
1%
#5615100
0%
#5633450
b110 .
1%
#5651800
0%
#5670150
b111 .
1%
#5688500
0%
#5706850
b1000 .
1%
#5725200
0%
#5743550
b1001 .
1%
#5761900
0%
#5780250
b1010 .
1%
#5798600
0%
#5816950
b1011 .
1%
#5835300
0%
#5853650
b1100 .
1%
#5872000
0%
#5890350
b1101 .
1%
#5908700
0%
#5927050
b1110 .
1%
#5945400
0%
#5963750
b1111 .
1%
#5982100
0%
#6000450
b10000 .
1%
#6018800
0%
#6037150
b10001 .
1%
#6055500
0%
#6073850
b10010 .
1%
#6092200
0%
#6110550
b10011 .
1%
#6128900
0%
#6147250
b10100 .
1%
#6165600
0%
#6183950
b10101 .
1%
#6202300
0%
#6220650
b10110 .
1%
#6239000
0%
#6257350
b10111 .
1%
#6275700
0%
#6294050
b11000 .
1%
#6312400
0%
#6330750
b11001 .
1%
#6349100
0%
#6367450
b11010 .
1%
#6385800
0%
#6404150
b11011 .
1%
#6422500
0%
#6440850
b11100 .
1%
#6459200
0%
#6477550
b11101 .
1%
#6495900
0%
#6514250
b11110 .
1%
#6532600
0%
#6550950
b11111 .
1%
#6569300
0%
#6587650
b100000 .
1%
#6606000
0%
#6624350
b100001 .
1%
#6642700
0%
#6661050
b100010 .
1%
#6679400
0%
#6697750
b100011 .
1%
#6716100
0%
#6734450
b100100 .
1%
#6752800
0%
#6771150
b100101 .
1%
#6789500
0%
#6807850
b100110 .
1%
#6826200
0%
#6844550
b100111 .
1%
#6862900
0%
#6881250
b101000 .
1%
#6899600
0%
#6917950
b101001 .
1%
#6936300
0%
#6954650
b101010 .
1%
#6973000
0%
#6991350
b101011 .
1%
#7009700
0%
#7028050
b101100 .
1%
#7046400
0%
#7064750
b101101 .
1%
#7083100
0%
#7101450
b101110 .
1%
#7119800
0%
#7138150
b101111 .
1%
#7156500
0%
#7174850
b110000 .
1%
#7193200
0%
#7211550
b110001 .
1%
#7229900
0%
#7248250
b110010 .
1%
#7266600
0%
#7284950
b110011 .
1%
#7303300
0%
#7321650
b110100 .
1%
#7340000
0%
#7358350
b110101 .
1%
#7376700
0%
#7395050
b110110 .
1%
#7413400
0%
#7431750
b110111 .
1%
#7450100
0%
#7468450
b111000 .
1%
#7486800
0%
#7505150
b111001 .
1%
#7523500
0%
#7541850
b111010 .
1%
#7560200
0%
#7578550
b111011 .
1%
#7596900
0%
#7615250
b111100 .
1%
#7633600
0%
#7651950
b111101 .
1%
#7670300
0%
#7688650
b111110 .
1%
#7707000
0%
#7725350
b111111 .
1%
#7743700
0%
#7762050
b1000000 .
1%
#7780400
0%
#7798750
b1000001 .
1%
#7817100
0%
#7835450
b1000010 .
1%
#7853800
0%
#7872150
b1000011 .
1%
#7890500
0%
#7908850
b1000100 .
1%
#7927200
0%
#7945550
b1000101 .
1%
#7963900
0%
#7982250
b1000110 .
1%
#8000600
0%
#8018950
b1000111 .
1%
#8037300
0%
#8055650
b1001000 .
1%
#8074000
0%
#8092350
b1001001 .
1%
#8110700
0%
#8129050
b1001010 .
1%
#8147400
0%
#8165750
b1001011 .
1%
#8184100
0%
#8202450
b1001100 .
1%
#8220800
0%
#8239150
b1001101 .
1%
#8257500
0%
#8275850
b1001110 .
1%
#8294200
0%
#8312550
b1001111 .
1%
#8330900
0%
#8349250
b1010000 .
1%
#8367600
0%
#8385950
b1010001 .
1%
#8404300
0%
#8422650
b1010010 .
1%
#8441000
0%
#8459350
b1010011 .
1%
#8477700
0%
#8496050
b1010100 .
1%
#8514400
0%
#8532750
b1010101 .
1%
#8551100
0%
#8569450
b1010110 .
1%
#8587800
0%
#8606150
b1010111 .
1%
#8624500
0%
#8642850
b1011000 .
1%
#8661200
0%
#8679550
b1011001 .
1%
#8697900
0%
#8716250
b1011010 .
1%
#8734600
0%
#8752950
b1011011 .
1%
#8771300
0%
#8789650
b1011100 .
1%
#8808000
0%
#8826350
b1011101 .
1%
#8844700
0%
#8863050
b1011110 .
1%
#8881400
0%
#8899750
b1011111 .
1%
#8918100
0%
#8936450
b1100000 .
1%
#8954800
0%
#8973150
b1100001 .
1%
#8991500
0%
#9009850
b1100010 .
1%
#9028200
0%
#9046550
b1100011 .
1%
#9064900
0%
#9083250
b1100100 .
1%
#9101600
0%
#9119950
b1100101 .
1%
#9138300
0%
#9156650
b1100110 .
1%
#9175000
0%
#9193350
b1100111 .
1%
#9211700
0%
#9230050
b1101000 .
1%
#9248400
0%
#9266750
b1101001 .
1%
#9285100
0%
#9303450
b1101010 .
1%
#9321800
0%
#9340150
b1101011 .
1%
#9358500
0%
#9376850
b1101100 .
1%
#9395200
0%
#9413550
b1101101 .
1%
#9431900
0%
#9450250
b1101110 .
1%
#9468600
0%
#9486950
b1101111 .
1%
#9505300
0%
#9523650
b1110000 .
1%
#9542000
0%
#9560350
b1110001 .
1%
#9578700
0%
#9597050
b1110010 .
1%
#9615400
0%
#9633750
b1110011 .
1%
#9652100
0%
#9670450
b1110100 .
1%
#9688800
0%
#9707150
b1110101 .
1%
#9721000
1#
b0 9
#9725500
0%
#9743850
b1110110 .
1%
#9762200
0%
#9780550
b1110111 .
1%
#9798900
0%
#9817250
b1111000 .
1%
#9835600
0%
#9853950
b1111001 .
1%
#9872300
0%
#9890650
b1111010 .
1%
#9909000
0%
#9927350
b1111011 .
1%
#9945700
0%
#9964050
b1111100 .
1%
#9982400
0%
#10000750
b1111101 .
1%
#10019100
0%
#10037450
b1111110 .
1%
#10055800
0%
#10074150
b1111111 .
1%
#10092500
0%
#10110850
b10000000 .
1%
#10129200
0%
#10147550
b10000001 .
1%
#10165900
0%
#10184250
b10000010 .
1%
#10202600
0%
#10220950
b10000011 .
1%
#10239300
0%
#10257650
b10000100 .
1%
#10276000
0%
#10294350
b10000101 .
1%
#10312700
0%
#10331050
b10000110 .
1%
#10349400
0%
#10367750
b10000111 .
1%
#10386100
0%
#10404450
b10001000 .
1%
#10422800
0%
#10441150
b10001001 .
1%
#10459500
0%
#10477850
b10001010 .
1%
#10496200
0%
#10514550
b10001011 .
1%
#10532900
0%
#10551250
b10001100 .
1%
#10569600
0%
#10587950
b10001101 .
1%
#10606300
0%
#10624650
b10001110 .
1%
#10643000
0%
#10661350
b10001111 .
1%
#10679700
0%
#10698050
b10010000 .
1%
#10716400
0%
#10734750
b10010001 .
1%
#10753100
0%
#10771450
b10010010 .
1%
#10789800
0%
#10808150
b10010011 .
1%
#10826500
0%
#10844850
b10010100 .
1%
#10863200
0%
#10881550
b10010101 .
1%
#10899900
0%
#10918250
b10010110 .
1%
#10936600
0%
#10954950
b10010111 .
1%
#10973300
0%
#10991650
b10011000 .
1%
#11010000
0%
#11028350
b10011001 .
1%
#11046700
0%
#11065050
b10011010 .
1%
#11083400
0%
#11101750
b10011011 .
1%
#11120100
0%
#11138450
b10011100 .
1%
#11156800
0%
#11175150
b10011101 .
1%
#11193500
0%
#11211850
b10011110 .
1%
#11230200
0%
#11248550
b10011111 .
1%
#11266900
0%
#11285250
b10100000 .
1%
#11303600
0%
#11321950
b10100001 .
1%
#11340300
0%
#11358650
b10100010 .
1%
#11377000
0%
#11395350
b10100011 .
1%
#11413700
0%
#11432050
b10100100 .
1%
#11450400
0%
#11468750
b10100101 .
1%
#11487100
0%
#11505450
b10100110 .
1%
#11523800
0%
#11542150
b10100111 .
1%
#11560500
0%
#11578850
b10101000 .
1%
#11597200
0%
#11615550
b10101001 .
1%
#11633900
0%
#11652250
b10101010 .
1%
#11670600
0%
#11688950
b10101011 .
1%
#11707300
0%
#11725650
b10101100 .
1%
#11744000
0%
#11762350
b10101101 .
1%
#11780700
0%
#11799050
b10101110 .
1%
#11817400
0%
#11835750
b10101111 .
1%
#11854100
0%
#11872450
b10110000 .
1%
#11890800
0%
#11909150
b10110001 .
1%
#11927500
0%
#11945850
b10110010 .
1%
#11964200
0%
#11982550
b10110011 .
1%
#12000900
0%
#12019250
b10110100 .
1%
#12037600
0%
#12055950
b10110101 .
1%
#12074300
0%
#12092650
b10110110 .
1%
#12111000
0%
#12129350
b10110111 .
1%
#12147700
0%
#12166050
b10111000 .
1%
#12184400
0%
#12202750
b10111001 .
1%
#12221100
0%
#12239450
b10111010 .
1%
#12257800
0%
#12276150
b10111011 .
1%
#12294500
0%
#12312850
b10111100 .
1%
#12331200
0%
#12349550
b10111101 .
1%
#12367900
0%
#12386250
b10111110 .
1%
#12404600
0%
#12422950
b10111111 .
1%
#12441300
0%
#12459650
b11000000 .
1%
#12478000
0%
#12496350
b11000001 .
1%
#12514700
0%
#12533050
b11000010 .
1%
#12551400
0%
#12569750
b11000011 .
1%
#12588100
0%
#12606450
b11000100 .
1%
#12624800
0%
#12643150
b11000101 .
1%
#12661500
0%
#12679850
b11000110 .
1%
#12698200
0%
#12716550
b11000111 .
1%
#12734900
0%
#12753250
b11001000 .
1%
#12771600
0%
#12789950
b11001001 .
1%
#12808300
0%
#12826650
b11001010 .
1%
#12845000
0%
#12863350
b11001011 .
1%
#12881700
0%
#12900050
b11001100 .
1%
#12918400
0%
#12936750
b11001101 .
1%
#12955100
0%
#12973450
b11001110 .
1%
#12991800
0%
#13010150
b11001111 .
1%
#13028500
0%
#13046850
b11010000 .
1%
#13065200
0%
#13083550
b11010001 .
1%
#13101900
0%
#13120250
b11010010 .
1%
#13138600
0%
#13156950
b11010011 .
1%
#13175300
0%
#13193650
b11010100 .
1%
#13212000
0%
#13230350
b11010101 .
1%
#13248700
0%
#13267050
b11010110 .
1%
#13285400
0%
#13303750
b11010111 .
1%
#13322100
0%
#13340450
b11011000 .
1%
#13358800
0%
#13377150
b11011001 .
1%
#13395500
0%
#13413850
b11011010 .
1%
#13432200
0%
#13450550
b11011011 .
1%
#13468900
0%
#13487250
b11011100 .
1%
#13505600
0%
#13523950
b11011101 .
1%
#13542300
0%
#13560650
b11011110 .
1%
#13579000
0%
#13597350
b11011111 .
1%
#13615700
0%
#13634050
b11100000 .
1%
#13652400
0%
#13670750
b11100001 .
1%
#13689100
0%
#13707450
b11100010 .
1%
#13725800
0%
#13744150
b11100011 .
1%
#13762500
0%
#13780850
b11100100 .
1%
#13799200
0%
#13817550
b11100101 .
1%
#13835900
0%
#13854250
b11100110 .
1%
#13872600
0%
#13890950
b11100111 .
1%
#13909300
0%
#13927650
b11101000 .
1%
#13946000
0%
#13964350
b11101001 .
1%
#13982700
0%
#14001050
b1 0
b1 4
b0 .
1%
#14019400
0%
#14037750
b1 .
1%
#14056100
0%
#14074450
b10 .
1%
#14092800
0%
#14111150
b11 .
1%
#14129500
0%
#14147850
b100 .
1%
#14166200
0%
#14184550
b101 .
1%
#14202900
0%
#14221250
b110 .
1%
#14239600
0%
#14257950
b111 .
1%
#14276300
0%
#14294650
b1000 .
1%
#14313000
0%
#14331350
b1001 .
1%
#14349700
0%
#14368050
b1010 .
1%
#14386400
0%
#14404750
b1011 .
1%
#14423100
0%
#14441450
b1100 .
1%
#14459800
0%
#14478150
b1101 .
1%
#14496500
0%
#14514850
b1110 .
1%
#14533200
0%
#14551550
b1111 .
1%
#14569900
0%
#14588250
b10000 .
1%
#14606600
0%
#14624950
b10001 .
1%
#14643300
0%
#14661650
b10010 .
1%
#14680000
0%
#14698350
b10011 .
1%
#14716700
0%
#14735050
b10100 .
1%
#14753400
0%
#14771750
b10101 .
1%
#14790100
0%
#14808450
b10110 .
1%
#14826800
0%
#14845150
b10111 .
1%
#14863500
0%
#14881850
b11000 .
1%
#14900200
0%
#14918550
b11001 .
1%
#14936900
0%
#14955250
b11010 .
1%
#14973600
0%
#14991950
b11011 .
1%
#15010300
0%
#15028650
b11100 .
1%
#15047000
0%
#15065350
b11101 .
1%
#15083700
0%
#15102050
b11110 .
1%
#15120400
0%
#15138750
b11111 .
1%
#15157100
0%
#15175450
b100000 .
1%
#15193800
0%
#15212150
b100001 .
1%
#15230500
0%
#15248850
b100010 .
1%
#15267200
0%
#15285550
b100011 .
1%
#15303900
0%
#15322250
b100100 .
1%
#15340600
0%
#15358950
b100101 .
1%
#15377300
0%
#15395650
b100110 .
1%
#15414000
0%
#15432350
b100111 .
1%
#15450700
0%
#15469050
b101000 .
1%
#15487400
0%
#15505750
b101001 .
1%
#15524100
0%
#15542450
b101010 .
1%
#15560800
0%
#15579150
b101011 .
1%
#15597500
0%
#15615850
b101100 .
1%
#15634200
0%
#15652550
b101101 .
1%
#15670900
0%
#15689250
b101110 .
1%
#15707600
0%
#15725950
b101111 .
1%
#15744300
0%
#15762650
b110000 .
1%
#15781000
0%
#15799350
b110001 .
1%
#15817700
0%
#15836050
b110010 .
1%
#15854400
0%
#15872750
b110011 .
1%
#15891100
0%
#15909450
b110100 .
1%
#15927800
0%
#15946150
b110101 .
1%
#15964500
0%
#15982850
b110110 .
1%
#16001200
0%
#16019550
b110111 .
1%
#16037900
0%
#16056250
b111000 .
1%
#16074600
0%
#16092950
b111001 .
1%
#16111300
0%
#16129650
b111010 .
1%
#16148000
0%
#16166350
b111011 .
1%
#16184700
0%
#16203050
b111100 .
1%
#16221400
0%
#16239750
b111101 .
1%
#16258100
0%
#16276450
b111110 .
1%
#16294800
0%
#16313150
b111111 .
1%
#16331500
0%
#16349850
b1000000 .
1%
#16368200
0%
#16386550
b1000001 .
1%
#16404900
0%
#16423250
b1000010 .
1%
#16441600
0%
#16459950
b1000011 .
1%
#16478300
0%
#16496650
b1000100 .
1%
#16515000
0%
#16533350
b1000101 .
1%
#16551700
0%
#16570050
b1000110 .
1%
#16588400
0%
#16606750
b1000111 .
1%
#16625100
0%
#16643450
b1001000 .
1%
#16661800
0%
#16680150
b1001001 .
1%
#16698500
0%
#16716850
b1001010 .
1%
#16735200
0%
#16753550
b1001011 .
1%
#16771900
0%
#16790250
b1001100 .
1%
#16808600
0%
#16826950
b1001101 .
1%
#16845300
0%
#16863650
b1001110 .
1%
#16882000
0%
#16900350
b1001111 .
1%
#16918700
0%
#16937050
b1010000 .
1%
#16955400
0%
#16973750
b1010001 .
1%
#16992100
0%
#17010450
b1010010 .
1%
#17028800
0%
#17047150
b1010011 .
1%
#17065500
0%
#17083850
b1010100 .
1%
#17102200
0%
#17120550
b1010101 .
1%
#17138900
0%
#17157250
b1010110 .
1%
#17175600
0%
#17193950
b1010111 .
1%
#17212300
0%
#17230650
b1011000 .
1%
#17249000
0%
#17267350
b1011001 .
1%
#17285700
0%
#17304050
b1011010 .
1%
#17322400
0%
#17340750
b1011011 .
1%
#17359100
0%
#17377450
b1011100 .
1%
#17395800
0%
#17414150
b1011101 .
1%
#17432500
0%
#17450850
b1011110 .
1%
#17469200
0%
#17487550
b1011111 .
1%
#17505900
0%
#17524250
b1100000 .
1%
#17542600
0%
#17560950
b1100001 .
1%
#17579300
0%
#17597650
b1100010 .
1%
#17616000
0%
#17634350
b1100011 .
1%
#17652700
0%
#17671050
b1100100 .
1%
#17689400
0%
#17707750
b1100101 .
1%
#17726100
0%
#17744450
b1100110 .
1%
#17762800
0%
#17781150
b1100111 .
1%
#17799500
0%
