Projects/WS2812/main.v
module top (
    input wire clk,
    output wire led0,
    input wire btn2,
    output wire WS2812_TX
);

reg [24:0] time_counter;
reg rdy;

localparam clk_freq = 27000000;
localparam t_ms = 500;
localparam t_ms_ticks = (clk_freq / 1000) * t_ms;

wire [23:0] color;

reg [31:0] freq_div;
reg [31:0] compare;

// Time counter logic to trigger `rdy` signal
always @(posedge clk or posedge btn2) begin
    if (btn2) begin
        time_counter <= 0;  // Reset counter on `btn2`
        rdy <= 0;           // Reset `rdy` when `btn2` is pressed
        freq_div <= 1000;
        compare <= 0;
    end else begin
        time_counter <= time_counter + 1;

        if(time_counter & 16'hffff) begin
            compare <= compare + 1;
            if (compare == 1000) begin
                compare <= 0;
            end
        end

        if (time_counter == t_ms_ticks) begin
            rdy <= 1;   // Set `rdy` high

        end else if (time_counter == t_ms_ticks + 32) begin
            rdy <= 0;   // Reset `rdy` and counter
            time_counter <= 0;
        end
    end
end

// WS2812 instantiation
WS2812 ws2812 (
    .clk(clk),
    .color(color),
    .tx(WS2812_TX),
    .rst(btn2),
    .set(rdy)
);

// LFSR instantiation
LFSR lfsr (
    .clk(rdy),
    .DATA(color),
    .reset(btn2)
);


PWM pwm (
    .clk(clk),
    .op_pin(led0),
    .freq_div(freq_div),
    .compare(compare),
    .rst(btn2)
    );

endmodule

module WS2812 (
    input wire clk,
    input wire [23:0] color,  // Proper input declaration
    output reg tx,
    input wire rst,
    input wire set
);

parameter clk_freq = 27000000;

// Timing parameters in ticks
parameter T0_H_ticks = 9;            // 350ns
parameter T0_L_ticks = 9 + 22;       // 800ns
parameter T1_H_ticks = 19;           // 700ns
parameter T1_L_ticks = 19 + 16;      // 600ns
parameter RFSH_ticks = 16;           // 50us

reg [5:0] bit_indexer;
reg [5:0] tick_counter;
reg [2:0] state;

parameter IDLE = 0, TX = 1, RFSH = 2;

always @(posedge clk) begin
    if (rst) begin
        bit_indexer <= 0;
        tick_counter <= 0;
        state <= IDLE;               // Ensure state initializes to IDLE
        tx <= 0;
    end else begin
        case (state)
            IDLE: begin
                tx <= 0;
                bit_indexer <= 0;
                tick_counter <= 0;
                if (set) begin
                    state <= TX;      // Start transmission when 'set' is high
                end
            end

            TX: begin
                if (color[23 - bit_indexer] == 0) begin  // Check current bit (MSB first)
                    tick_counter <= tick_counter + 1;
                    if (tick_counter < T0_H_ticks) begin
                        tx <= 1;      // High for T0_H_ticks
                    end else if (tick_counter < T0_L_ticks) begin
                        tx <= 0;      // Low for T0_L_ticks
                    end else begin
                        tick_counter <= 0;
                        bit_indexer <= bit_indexer + 1; // Move to the next bit
                        tx <= 1;
                    end
                end else begin
                    tick_counter <= tick_counter + 1;
                    if (tick_counter < T1_H_ticks) begin
                        tx <= 1;      // High for T1_H_ticks
                    end else if (tick_counter < T1_L_ticks) begin
                        tx <= 0;      // Low for T1_L_ticks
                    end else begin
                        tick_counter <= 0;
                        bit_indexer <= bit_indexer + 1; // Move to the next bit
                        tx <= 1;
                    end
                end

                if (bit_indexer == 24) begin
                    state <= RFSH;    // Move to refresh state after 24 bits
                end
            end

            RFSH: begin
                tx <= 0;              // Keep the line low
                tick_counter <= tick_counter + 1;
                if (tick_counter == RFSH_ticks) begin
                    tick_counter <= 0;
                    state <= IDLE;    // Return to idle after refresh time
                end
            end
        endcase
    end
end

endmodule


module LFSR (
    output reg [23:0] DATA,
    input wire clk,
    input wire reset
);


always @(posedge clk or posedge reset) begin
    if (reset == 1) begin
        time_counter <= 0;
        DATA <= 24'b101101001011010010110100;
    end else begin
        DATA[0]  <= DATA[23];  
        DATA[1]  <= DATA[0] ^ DATA[23];
        DATA[2]  <= DATA[1];
        DATA[3]  <= DATA[2];
        DATA[4]  <= DATA[3];
        DATA[5]  <= DATA[4];
        DATA[6]  <= DATA[5] ^ DATA[23];
        DATA[7]  <= DATA[6] ^ DATA[23];
        DATA[8]  <= DATA[7];
        DATA[9]  <= DATA[8] ^ DATA[23];
        DATA[10] <= DATA[9];
        DATA[11] <= DATA[10];
        DATA[12] <= DATA[11];
        DATA[13] <= DATA[12];
        DATA[14] <= DATA[13];
        DATA[15] <= DATA[14];
        DATA[16] <= DATA[15];
        DATA[17] <= DATA[16] ^ DATA[23];  // Feedback XOR at tap 17
        DATA[18] <= DATA[17];
        DATA[19] <= DATA[18] ^ DATA[23];
        DATA[20] <= DATA[19];
        DATA[21] <= DATA[20];
        DATA[22] <= DATA[21] ^ DATA[23];  // Feedback XOR at tap 22
        DATA[23] <= DATA[22] ^ DATA[23];  // Feedback XOR at tap 23
    end
end
    
endmodule

module PWM (
    input wire clk,
    input wire [31:0] freq_div,
    input wire [31:0] compare,
    output reg op_pin,
    input wire rst
);

reg [31:0] tick_counter;

always @(posedge clk ) begin
    if(rst)
        tick_counter <= 0;
    tick_counter <= tick_counter + 1;
    if (tick_counter < compare) begin
        op_pin <= 1;
    end else if (tick_counter < freq_div) begin
        op_pin <= 0;
    end else begin
        tick_counter <= 0;
    end
end
    
endmodule

Projects/WS2812/tb/WS2812_tb.v
module WS2812_tb;

    // Testbench signals
    reg clk;
    reg rst;
    reg set;
    reg [23:0] color;
    wire tx;

    // Instantiate the WS2812 module
    WS2812 uut (
        .clk(clk),
        .rst(rst),
        .set(set),
        .color(color),
        .tx(tx)
    );

    // Clock generation: 27 MHz clock, period = 37 ns
    always #18.5 clk = ~clk;

    initial begin
        // Initialize signals
        clk = 0;
        rst = 1;      // Start with reset asserted
        set = 0;
        color = 24'h000000;  // Default color (black)

        // Reset the system
        #100 rst = 0;  // Release reset after 100 ns

        // Apply stimulus: Set a color and trigger the transmission
        #50 set = 1;
        color = 24'hFF0000;  // Red color
        #100 set = 0;

        // Wait for a few clock cycles
        #5000;

        // Apply another color
        #50 set = 1;
        color = 24'h00FF00;  // Green color
        #100 set = 0;

        // Wait again for a few clock cycles
        #5000;

        // End the simulation
        $finish;
    end

    // Monitor the tx signal
    initial begin
        $monitor("At time %t: tx = %b", $time, tx);
    end

    // Dump waveform for analysis in a simulator like GTKWave
    initial begin
        $dumpfile("WS2812_tb.vcd");
        $dumpvars(0, WS2812_tb);
    end

endmodule

Projects/WS2812/tb/WS2812_tb.vcd
$date
	Sun Sep 29 02:25:31 2024
$end
$version
	Icarus Verilog
$end
$timescale
	1s
$end
$scope module WS2812_tb $end
$var wire 1 ! tx $end
$var reg 1 " clk $end
$var reg 24 # color [23:0] $end
$var reg 1 $ rst $end
$var reg 1 % set $end
$scope module uut $end
$var wire 1 " clk $end
$var wire 24 & color [23:0] $end
$var wire 1 $ rst $end
$var wire 1 % set $end
$var parameter 32 ' IDLE $end
$var parameter 32 ( RFSH $end
$var parameter 32 ) RFSH_ticks $end
$var parameter 32 * T0_H_ticks $end
$var parameter 33 + T0_L_ticks $end
$var parameter 32 , T1_H_ticks $end
$var parameter 33 - T1_L_ticks $end
$var parameter 32 . TX $end
$var parameter 32 / clk_freq $end
$var reg 6 0 bit_indexer [5:0] $end
$var reg 3 1 state [2:0] $end
$var reg 6 2 tick_counter [5:0] $end
$var reg 1 ! tx $end
$upscope $end
$upscope $end
$enddefinitions $end
$comment Show the parameter values. $end
$dumpall
b1100110111111110011000000 /
b1 .
b100011 -
b10011 ,
b11111 +
b1001 *
b10000 )
b10 (
b0 '
$end
#0
$dumpvars
bx 2
bx 1
bx 0
b0 &
0%
1$
b0 #
0"
x!
$end
#19
0!
b0 1
b0 2
b0 0
1"
#38
0"
#57
1"
#76
0"
#95
1"
#100
0$
#114
0"
#133
1"
#150
b111111110000000000000000 #
b111111110000000000000000 &
1%
#152
0"
#171
b1 1
1"
#190
0"
#209
1!
b1 2
1"
#228
0"
#247
b10 2
1"
#250
0%
#266
0"
#285
b11 2
1"
#304
0"
#323
b100 2
1"
#342
0"
#361
b101 2
1"
#380
0"
#399
b110 2
1"
#418
0"
#437
b111 2
1"
#456
0"
#475
b1000 2
1"
#494
0"
#513
b1001 2
1"
#532
0"
#551
b1010 2
1"
#570
0"
#589
b1011 2
1"
#608
0"
#627
b1100 2
1"
#646
0"
#665
b1101 2
1"
#684
0"
#703
b1110 2
1"
#722
0"
#741
b1111 2
1"
#760
0"
#779
b10000 2
1"
#798
0"
#817
b10001 2
1"
#836
0"
#855
b10010 2
1"
#874
0"
#893
b10011 2
1"
#912
0"
#931
0!
b10100 2
1"
#950
0"
#969
b10101 2
1"
#988
0"
#1007
b10110 2
1"
#1026
0"
#1045
b10111 2
1"
#1064
0"
#1083
b11000 2
1"
#1102
0"
#1121
b11001 2
1"
#1140
0"
#1159
b11010 2
1"
#1178
0"
#1197
b11011 2
1"
#1216
0"
#1235
b11100 2
1"
#1254
0"
#1273
b11101 2
1"
#1292
0"
#1311
b11110 2
1"
#1330
0"
#1349
b11111 2
1"
#1368
0"
#1387
b100000 2
1"
#1406
0"
#1425
b100001 2
1"
#1444
0"
#1463
b100010 2
1"
#1482
0"
#1501
b100011 2
1"
#1520
0"
#1539
1!
b1 0
b0 2
1"
#1558
0"
#1577
b1 2
1"
#1596
0"
#1615
b10 2
1"
#1634
0"
#1653
b11 2
1"
#1672
0"
#1691
b100 2
1"
#1710
0"
#1729
b101 2
1"
#1748
0"
#1767
b110 2
1"
#1786
0"
#1805
b111 2
1"
#1824
0"
#1843
b1000 2
1"
#1862
0"
#1881
b1001 2
1"
#1900
0"
#1919
b1010 2
1"
#1938
0"
#1957
b1011 2
1"
#1976
0"
#1995
b1100 2
1"
#2014
0"
#2033
b1101 2
1"
#2052
0"
#2071
b1110 2
1"
#2090
0"
#2109
b1111 2
1"
#2128
0"
#2147
b10000 2
1"
#2166
0"
#2185
b10001 2
1"
#2204
0"
#2223
b10010 2
1"
#2242
0"
#2261
b10011 2
1"
#2280
0"
#2299
0!
b10100 2
1"
#2318
0"
#2337
b10101 2
1"
#2356
0"
#2375
b10110 2
1"
#2394
0"
#2413
b10111 2
1"
#2432
0"
#2451
b11000 2
1"
#2470
0"
#2489
b11001 2
1"
#2508
0"
#2527
b11010 2
1"
#2546
0"
#2565
b11011 2
1"
#2584
0"
#2603
b11100 2
1"
#2622
0"
#2641
b11101 2
1"
#2660
0"
#2679
b11110 2
1"
#2698
0"
#2717
b11111 2
1"
#2736
0"
#2755
b100000 2
1"
#2774
0"
#2793
b100001 2
1"
#2812
0"
#2831
b100010 2
1"
#2850
0"
#2869
b100011 2
1"
#2888
0"
#2907
1!
b10 0
b0 2
1"
#2926
0"
#2945
b1 2
1"
#2964
0"
#2983
b10 2
1"
#3002
0"
#3021
b11 2
1"
#3040
0"
#3059
b100 2
1"
#3078
0"
#3097
b101 2
1"
#3116
0"
#3135
b110 2
1"
#3154
0"
#3173
b111 2
1"
#3192
0"
#3211
b1000 2
1"
#3230
0"
#3249
b1001 2
1"
#3268
0"
#3287
b1010 2
1"
#3306
0"
#3325
b1011 2
1"
#3344
0"
#3363
b1100 2
1"
#3382
0"
#3401
b1101 2
1"
#3420
0"
#3439
b1110 2
1"
#3458
0"
#3477
b1111 2
1"
#3496
0"
#3515
b10000 2
1"
#3534
0"
#3553
b10001 2
1"
#3572
0"
#3591
b10010 2
1"
#3610
0"
#3629
b10011 2
1"
#3648
0"
#3667
0!
b10100 2
1"
#3686
0"
#3705
b10101 2
1"
#3724
0"
#3743
b10110 2
1"
#3762
0"
#3781
b10111 2
1"
#3800
0"
#3819
b11000 2
1"
#3838
0"
#3857
b11001 2
1"
#3876
0"
#3895
b11010 2
1"
#3914
0"
#3933
b11011 2
1"
#3952
0"
#3971
b11100 2
1"
#3990
0"
#4009
b11101 2
1"
#4028
0"
#4047
b11110 2
1"
#4066
0"
#4085
b11111 2
1"
#4104
0"
#4123
b100000 2
1"
#4142
0"
#4161
b100001 2
1"
#4180
0"
#4199
b100010 2
1"
#4218
0"
#4237
b100011 2
1"
#4256
0"
#4275
1!
b11 0
b0 2
1"
#4294
0"
#4313
b1 2
1"
#4332
0"
#4351
b10 2
1"
#4370
0"
#4389
b11 2
1"
#4408
0"
#4427
b100 2
1"
#4446
0"
#4465
b101 2
1"
#4484
0"
#4503
b110 2
1"
#4522
0"
#4541
b111 2
1"
#4560
0"
#4579
b1000 2
1"
#4598
0"
#4617
b1001 2
1"
#4636
0"
#4655
b1010 2
1"
#4674
0"
#4693
b1011 2
1"
#4712
0"
#4731
b1100 2
1"
#4750
0"
#4769
b1101 2
1"
#4788
0"
#4807
b1110 2
1"
#4826
0"
#4845
b1111 2
1"
#4864
0"
#4883
b10000 2
1"
#4902
0"
#4921
b10001 2
1"
#4940
0"
#4959
b10010 2
1"
#4978
0"
#4997
b10011 2
1"
#5016
0"
#5035
0!
b10100 2
1"
#5054
0"
#5073
b10101 2
1"
#5092
0"
#5111
b10110 2
1"
#5130
0"
#5149
b10111 2
1"
#5168
0"
#5187
b11000 2
1"
#5206
0"
#5225
b11001 2
1"
#5244
0"
#5263
b11010 2
1"
#5282
0"
#5300
b1111111100000000 #
b1111111100000000 &
1%
#5301
b11011 2
1"
#5320
0"
#5339
b11100 2
1"
#5358
0"
#5377
b11101 2
1"
#5396
0"
#5400
0%
#5415
b11110 2
1"
#5434
0"
#5453
b11111 2
1"
#5472
0"
#5491
1!
b100 0
b0 2
1"
#5510
0"
#5529
b1 2
1"
#5548
0"
#5567
b10 2
1"
#5586
0"
#5605
b11 2
1"
#5624
0"
#5643
b100 2
1"
#5662
0"
#5681
b101 2
1"
#5700
0"
#5719
b110 2
1"
#5738
0"
#5757
b111 2
1"
#5776
0"
#5795
b1000 2
1"
#5814
0"
#5833
b1001 2
1"
#5852
0"
#5871
0!
b1010 2
1"
#5890
0"
#5909
b1011 2
1"
#5928
0"
#5947
b1100 2
1"
#5966
0"
#5985
b1101 2
1"
#6004
0"
#6023
b1110 2
1"
#6042
0"
#6061
b1111 2
1"
#6080
0"
#6099
b10000 2
1"
#6118
0"
#6137
b10001 2
1"
#6156
0"
#6175
b10010 2
1"
#6194
0"
#6213
b10011 2
1"
#6232
0"
#6251
b10100 2
1"
#6270
0"
#6289
b10101 2
1"
#6308
0"
#6327
b10110 2
1"
#6346
0"
#6365
b10111 2
1"
#6384
0"
#6403
b11000 2
1"
#6422
0"
#6441
b11001 2
1"
#6460
0"
#6479
b11010 2
1"
#6498
0"
#6517
b11011 2
1"
#6536
0"
#6555
b11100 2
1"
#6574
0"
#6593
b11101 2
1"
#6612
0"
#6631
b11110 2
1"
#6650
0"
#6669
b11111 2
1"
#6688
0"
#6707
1!
b101 0
b0 2
1"
#6726
0"
#6745
b1 2
1"
#6764
0"
#6783
b10 2
1"
#6802
0"
#6821
b11 2
1"
#6840
0"
#6859
b100 2
1"
#6878
0"
#6897
b101 2
1"
#6916
0"
#6935
b110 2
1"
#6954
0"
#6973
b111 2
1"
#6992
0"
#7011
b1000 2
1"
#7030
0"
#7049
b1001 2
1"
#7068
0"
#7087
0!
b1010 2
1"
#7106
0"
#7125
b1011 2
1"
#7144
0"
#7163
b1100 2
1"
#7182
0"
#7201
b1101 2
1"
#7220
0"
#7239
b1110 2
1"
#7258
0"
#7277
b1111 2
1"
#7296
0"
#7315
b10000 2
1"
#7334
0"
#7353
b10001 2
1"
#7372
0"
#7391
b10010 2
1"
#7410
0"
#7429
b10011 2
1"
#7448
0"
#7467
b10100 2
1"
#7486
0"
#7505
b10101 2
1"
#7524
0"
#7543
b10110 2
1"
#7562
0"
#7581
b10111 2
1"
#7600
0"
#7619
b11000 2
1"
#7638
0"
#7657
b11001 2
1"
#7676
0"
#7695
b11010 2
1"
#7714
0"
#7733
b11011 2
1"
#7752
0"
#7771
b11100 2
1"
#7790
0"
#7809
b11101 2
1"
#7828
0"
#7847
b11110 2
1"
#7866
0"
#7885
b11111 2
1"
#7904
0"
#7923
1!
b110 0
b0 2
1"
#7942
0"
#7961
b1 2
1"
#7980
0"
#7999
b10 2
1"
#8018
0"
#8037
b11 2
1"
#8056
0"
#8075
b100 2
1"
#8094
0"
#8113
b101 2
1"
#8132
0"
#8151
b110 2
1"
#8170
0"
#8189
b111 2
1"
#8208
0"
#8227
b1000 2
1"
#8246
0"
#8265
b1001 2
1"
#8284
0"
#8303
0!
b1010 2
1"
#8322
0"
#8341
b1011 2
1"
#8360
0"
#8379
b1100 2
1"
#8398
0"
#8417
b1101 2
1"
#8436
0"
#8455
b1110 2
1"
#8474
0"
#8493
b1111 2
1"
#8512
0"
#8531
b10000 2
1"
#8550
0"
#8569
b10001 2
1"
#8588
0"
#8607
b10010 2
1"
#8626
0"
#8645
b10011 2
1"
#8664
0"
#8683
b10100 2
1"
#8702
0"
#8721
b10101 2
1"
#8740
0"
#8759
b10110 2
1"
#8778
0"
#8797
b10111 2
1"
#8816
0"
#8835
b11000 2
1"
#8854
0"
#8873
b11001 2
1"
#8892
0"
#8911
b11010 2
1"
#8930
0"
#8949
b11011 2
1"
#8968
0"
#8987
b11100 2
1"
#9006
0"
#9025
b11101 2
1"
#9044
0"
#9063
b11110 2
1"
#9082
0"
#9101
b11111 2
1"
#9120
0"
#9139
1!
b111 0
b0 2
1"
#9158
0"
#9177
b1 2
1"
#9196
0"
#9215
b10 2
1"
#9234
0"
#9253
b11 2
1"
#9272
0"
#9291
b100 2
1"
#9310
0"
#9329
b101 2
1"
#9348
0"
#9367
b110 2
1"
#9386
0"
#9405
b111 2
1"
#9424
0"
#9443
b1000 2
1"
#9462
0"
#9481
b1001 2
1"
#9500
0"
#9519
0!
b1010 2
1"
#9538
0"
#9557
b1011 2
1"
#9576
0"
#9595
b1100 2
1"
#9614
0"
#9633
b1101 2
1"
#9652
0"
#9671
b1110 2
1"
#9690
0"
#9709
b1111 2
1"
#9728
0"
#9747
b10000 2
1"
#9766
0"
#9785
b10001 2
1"
#9804
0"
#9823
b10010 2
1"
#9842
0"
#9861
b10011 2
1"
#9880
0"
#9899
b10100 2
1"
#9918
0"
#9937
b10101 2
1"
#9956
0"
#9975
b10110 2
1"
#9994
0"
#10013
b10111 2
1"
#10032
0"
#10051
b11000 2
1"
#10070
0"
#10089
b11001 2
1"
#10108
0"
#10127
b11010 2
1"
#10146
0"
#10165
b11011 2
1"
#10184
0"
#10203
b11100 2
1"
#10222
0"
#10241
b11101 2
1"
#10260
0"
#10279
b11110 2
1"
#10298
0"
#10317
b11111 2
1"
#10336
0"
#10355
1!
b1000 0
b0 2
1"
#10374
0"
#10393
b1 2
1"
